bountycountry.py
bountycountry-1.6.0.dist-info/LICENSE
bountycountry-1.6.0.dist-info/METADATA
bountycountry-1.6.0.dist-info/WHEEL
bountycountry-1.6.0.dist-info/top_level.txt
bountycountry-1.6.0.dist-info/RECORD
