Metadata-Version: 2.1
Name: bountycountry
Version: 1.6.0
Summary: A light weight client library for accessing the Bounty Country API
Home-page: https://github.com/bounty-country/bountycountry-python
Author: Bounty Country
Author-email: support@bountycountry.com
License: MIT
Project-URL: Documentation, https://bountycountry.com/apidocs
Project-URL: Source Code, https://github.com/bounty-country/bountycountry-python
Keywords: bounty bountycountry
Platform: UNKNOWN
Requires-Python: >=3
Requires-Dist: requests
